pyedb/__init__.py
pyedb/edb_logger.py
pyedb/exceptions.py
pyedb/siwave.py
pyedb/workflow.py
pyedb/common/__init__.py
pyedb/common/nets.py
pyedb/component_libraries/ansys_components.py
pyedb/configuration/__init__.py
pyedb/configuration/cfg_boundaries.py
pyedb/configuration/cfg_common.py
pyedb/configuration/cfg_components.py
pyedb/configuration/cfg_data.py
pyedb/configuration/cfg_general.py
pyedb/configuration/cfg_modeler.py
pyedb/configuration/cfg_nets.py
pyedb/configuration/cfg_operations.py
pyedb/configuration/cfg_package_definition.py
pyedb/configuration/cfg_padstacks.py
pyedb/configuration/cfg_pin_groups.py
pyedb/configuration/cfg_ports_sources.py
pyedb/configuration/cfg_s_parameter_models.py
pyedb/configuration/cfg_setup.py
pyedb/configuration/cfg_spice_models.py
pyedb/configuration/cfg_stackup.py
pyedb/configuration/cfg_terminals.py
pyedb/configuration/configuration.py
pyedb/dotnet/__init__.py
pyedb/dotnet/clr_module.py
pyedb/dotnet/edb.py
pyedb/dotnet/database/Variables.py
pyedb/dotnet/database/__init__.py
pyedb/dotnet/database/components.py
pyedb/dotnet/database/general.py
pyedb/dotnet/database/hfss.py
pyedb/dotnet/database/layout_obj_instance.py
pyedb/dotnet/database/layout_validation.py
pyedb/dotnet/database/materials.py
pyedb/dotnet/database/modeler.py
pyedb/dotnet/database/net_class.py
pyedb/dotnet/database/nets.py
pyedb/dotnet/database/padstack.py
pyedb/dotnet/database/siwave.py
pyedb/dotnet/database/source_excitations.py
pyedb/dotnet/database/stackup.py
pyedb/dotnet/database/cell/__init__.py
pyedb/dotnet/database/cell/cell.py
pyedb/dotnet/database/cell/connectable.py
pyedb/dotnet/database/cell/layout.py
pyedb/dotnet/database/cell/layout_obj.py
pyedb/dotnet/database/cell/voltage_regulator.py
pyedb/dotnet/database/cell/hierarchy/__init__.py
pyedb/dotnet/database/cell/hierarchy/component.py
pyedb/dotnet/database/cell/hierarchy/hierarchy_obj.py
pyedb/dotnet/database/cell/hierarchy/model.py
pyedb/dotnet/database/cell/hierarchy/netlist_model.py
pyedb-0.66.0.dist-info/licenses/LICENSE
pyedb-0.66.0.dist-info/WHEEL
pyedb-0.66.0.dist-info/METADATA
pyedb-0.66.0.dist-info/RECORD
