Metadata-Version: 2.4
Name: pyedb
Version: 0.66.0
Summary: Higher-Level Pythonic Ansys Electronics Data Base
Author-email: "ANSYS, Inc." <pyansys.core@ansys.com>
Maintainer-email: PyEDB developers <simon.vandenbrouck@ansys.com>
Requires-Python: >=3.8,<4
Classifier: Development Status :: 4 - Beta
Classifier: Intended Audience :: Science/Research
Classifier: Topic :: Scientific/Engineering :: Information Analysis
Classifier: License :: OSI Approved :: MIT License
Classifier: Operating System :: OS Independent
Classifier: Programming Language :: Python :: 3.8
Classifier: Programming Language :: Python :: 3.9
Classifier: Programming Language :: Python :: 3.10
Classifier: Programming Language :: Python :: 3.11
License-File: LICENSE
Requires-Dist: cffi>=1.16.0,<2.1; platform_system=='Linux'
Requires-Dist: pywin32 >= 303;platform_system=='Windows'
Requires-Dist: ansys-pythonnet >= 3.1.0rc4
Requires-Dist: dotnetcore2 ==3.1.23;platform_system=='Linux'
Requires-Dist: numpy>=1.20.0,<3
Requires-Dist: pandas>=1.1.0,<2.4
Requires-Dist: pydantic>=2.6.4,<2.13
Requires-Dist: Rtree >= 1.2.0
Requires-Dist: toml == 0.10.2
Requires-Dist: shapely
Requires-Dist: scikit-rf
Requires-Dist: ansys-edb-core>=0.2.0,<0.2.3
Requires-Dist: psutil
Requires-Dist: defusedxml>=0.7,<8.0
Requires-Dist: matplotlib>=3.5.0,<3.11
Requires-Dist: aiohttp>=3.8
Requires-Dist: python-socketio>=5.10
Requires-Dist: requests>=2.32,<3.0
Requires-Dist: ezdxf>=1.4.2
Requires-Dist: scipy>=1.13, <2.0
Requires-Dist: ansys-sphinx-theme[autoapi]>=1.0.0,<1.7 ; extra == "doc"
Requires-Dist: imageio>=2.30.0,<2.38 ; extra == "doc"
Requires-Dist: ipython>=8.13.0,<8.32 ; extra == "doc"
Requires-Dist: jupyterlab>=4.0.0,<4.6 ; extra == "doc"
Requires-Dist: jupytext>=1.16.0,<1.19 ; extra == "doc"
Requires-Dist: matplotlib>=3.5.0,<3.11 ; extra == "doc"
Requires-Dist: nbsphinx>=0.9.0,<0.10 ; extra == "doc"
Requires-Dist: nbconvert < 7.17 ; extra == "doc"
Requires-Dist: numpydoc==1.5.0 ; extra == "doc"
Requires-Dist: pypandoc>=1.10.0,<1.17 ; extra == "doc"
Requires-Dist: recommonmark ; extra == "doc"
Requires-Dist: Sphinx>=7.1.0,<8.3 ; extra == "doc"
Requires-Dist: sphinx-autobuild==2024.10.3 ; extra == "doc"
Requires-Dist: sphinx-copybutton>=0.5.0,<0.6 ; extra == "doc"
Requires-Dist: sphinx-gallery>=0.14.0,<0.20 ; extra == "doc"
Requires-Dist: sphinx_design>=0.4.0,<0.7 ; extra == "doc"
Requires-Dist: shapely ; extra == "doc"
Requires-Dist: matplotlib>=3.5.0,<3.11 ; extra == "tests"
Requires-Dist: mock>=5.1.0,<5.3 ; extra == "tests"
Requires-Dist: pytest>=7.4.0,<8.5 ; extra == "tests"
Requires-Dist: pytest-cov>=4.0.0,<7.1 ; extra == "tests"
Requires-Dist: pytest-xdist>=3.5.0,<3.7 ; extra == "tests"
Requires-Dist: scikit-rf ; extra == "tests"
Requires-Dist: shapely ; extra == "tests"
Project-URL: Bugs, https://github.com/ansys/pyedb/issues
Project-URL: Discussions, https://github.com/ansys/pyedb/discussions
Project-URL: Documentation, https://edb.docs.pyansys.com
Project-URL: Releases, https://github.com/ansys/pyedb/releases
Project-URL: Source, https://github.com/ansys/pyedb
Provides-Extra: doc
Provides-Extra: tests
